scubalspy/__init__.py
scubalspy/language_server.py
scubalspy/scubalspy_config.py
scubalspy/scubalspy_exceptions.py
scubalspy/scubalspy_logger.py
scubalspy/scubalspy_settings.py
scubalspy/scubalspy_types.py
scubalspy/scubalspy_utils.py
scubalspy/type_helpers.py
scubalspy/language_servers/clangd_language_server/clangd_language_server.py
scubalspy/language_servers/clangd_language_server/initialize_params.json
scubalspy/language_servers/clangd_language_server/runtime_dependencies.json
scubalspy/language_servers/dart_language_server/dart_language_server.py
scubalspy/language_servers/dart_language_server/initialize_params.json
scubalspy/language_servers/dart_language_server/runtime_dependencies.json
scubalspy/language_servers/eclipse_jdtls/eclipse_jdtls.py
scubalspy/language_servers/eclipse_jdtls/initialize_params.json
scubalspy/language_servers/eclipse_jdtls/runtime_dependencies.json
scubalspy/language_servers/gopls/gopls.py
scubalspy/language_servers/gopls/initialize_params.json
scubalspy/language_servers/kotlin_language_server/initialize_params.json
scubalspy/language_servers/kotlin_language_server/kotlin_language_server.py
scubalspy/language_servers/kotlin_language_server/runtime_dependencies.json
scubalspy/language_servers/omnisharp/initialize_params.json
scubalspy/language_servers/omnisharp/omnisharp.py
scubalspy/language_servers/omnisharp/runtime_dependencies.json
scubalspy/language_servers/omnisharp/workspace_did_change_configuration.json
scubalspy/language_servers/pyright/initialize_params.json
scubalspy/language_servers/pyright/pyright.py
scubalspy/language_servers/rust_analyzer/initialize_params.json
scubalspy/language_servers/rust_analyzer/runtime_dependencies.json
scubalspy/language_servers/rust_analyzer/rust_analyzer.py
scubalspy/language_servers/solargraph/initialize_params.json
scubalspy/language_servers/solargraph/runtime_dependencies.json
scubalspy/language_servers/solargraph/solargraph.py
scubalspy-0.0.23.dist-info/licenses/LICENSE
scubalspy-0.0.23.dist-info/WHEEL
scubalspy-0.0.23.dist-info/METADATA
scubalspy-0.0.23.dist-info/RECORD
